mikrotikrscparser/__init__.py
mikrotikrscparser/rscparser.py
mikrotikrscparser/statement.py
mikrotikrscparser-0.0.1.dist-info/LICENSE
mikrotikrscparser-0.0.1.dist-info/METADATA
mikrotikrscparser-0.0.1.dist-info/WHEEL
mikrotikrscparser-0.0.1.dist-info/top_level.txt
mikrotikrscparser-0.0.1.dist-info/RECORD
