Metadata-Version: 2.1
Name: mikrotikrscparser
Version: 0.0.1
Summary: MikroTik RSC file parser library
Home-page: https://github.com/muqiuq/mikrotikrscparser
Author: Philipp Albrecht
Author-email: philipp@uisa.ch
License: MIT
License-File: LICENSE
